tbot_base/__init__.py
tbot_base/admin.py
tbot_base/apps.py
tbot_base/bot.py
tbot_base/models.py
tbot_base/urls.py
tbot_base/views.py
django_tbot_base-1.0.1.dist-info/LICENSE
django_tbot_base-1.0.1.dist-info/METADATA
django_tbot_base-1.0.1.dist-info/WHEEL
django_tbot_base-1.0.1.dist-info/top_level.txt
django_tbot_base-1.0.1.dist-info/RECORD
