Metadata-Version: 2.1
Name: django-tbot-base
Version: 1.0.1
Summary: Django Telegram bot base config
Home-page: https://github.com/IvanRomanchenko/django-tbot-base
Author: Ivan Romanchenko
Author-email: vanvanych789@gmail.com
License: UNKNOWN
Platform: UNKNOWN
Classifier: Programming Language :: Python :: 3.10
Classifier: Framework :: Django :: 4.0
Classifier: License :: OSI Approved :: MIT License
Classifier: Operating System :: OS Independent
Requires-Python: >=3.6
License-File: LICENSE
Requires-Dist: Django (==4.0.2)
Requires-Dist: pyTelegramBotAPI (==4.4.0)
Requires-Dist: loguru (==0.6.0)
